topaztrainmetrics.py
topaztrainmetrics-1.2.dist-info/LICENSE
topaztrainmetrics-1.2.dist-info/METADATA
topaztrainmetrics-1.2.dist-info/WHEEL
topaztrainmetrics-1.2.dist-info/entry_points.txt
topaztrainmetrics-1.2.dist-info/top_level.txt
topaztrainmetrics-1.2.dist-info/RECORD
